mb_annotation/__init__.py
mb_annotation/bounding_box.py
mb_annotation/sam2.py
mb_annotation/utils.py
mb_annotation/version.py
mb_annotaion-1.0.18.dist-info/METADATA
mb_annotaion-1.0.18.dist-info/WHEEL
mb_annotaion-1.0.18.dist-info/top_level.txt
mb_annotaion-1.0.18.dist-info/RECORD
